{
  "version": "2.5.0",
  "summary": {
    "title": "Hospital Management System",
    "owner": "",
    "description": "",
    "id": 0
  },
  "detail": {
    "contributors": [],
    "diagrams": [
      {
        "id": 0,
        "title": "DFD",
        "diagramType": "STRIDE",
        "placeholder": "New STRIDE diagram description",
        "thumbnail": "./public/content/images/thumbnail.stride.jpg",
        "version": "2.5.0",
        "cells": [
          {
            "position": {
              "x": 50,
              "y": 500
            },
            "size": {
              "width": 112.5,
              "height": 60
            },
            "attrs": {
              "text": {
                "text": "Doctor/Nurse"
              },
              "body": {
                "stroke": "#333333",
                "strokeWidth": 1.5,
                "strokeDasharray": null
              }
            },
            "visible": true,
            "shape": "actor",
            "ports": {
              "groups": {
                "top": {
                  "position": "top",
                  "attrs": {
                    "circle": {
                      "r": 4,
                      "magnet": true,
                      "stroke": "#5F95FF",
                      "strokeWidth": 1,
                      "fill": "#fff",
                      "style": {
                        "visibility": "hidden"
                      }
                    }
                  }
                },
                "right": {
                  "position": "right",
                  "attrs": {
                    "circle": {
                      "r": 4,
                      "magnet": true,
                      "stroke": "#5F95FF",
                      "strokeWidth": 1,
                      "fill": "#fff",
                      "style": {
                        "visibility": "hidden"
                      }
                    }
                  }
                },
                "bottom": {
                  "position": "bottom",
                  "attrs": {
                    "circle": {
                      "r": 4,
                      "magnet": true,
                      "stroke": "#5F95FF",
                      "strokeWidth": 1,
                      "fill": "#fff",
                      "style": {
                        "visibility": "hidden"
                      }
                    }
                  }
                },
                "left": {
                  "position": "left",
                  "attrs": {
                    "circle": {
                      "r": 4,
                      "magnet": true,
                      "stroke": "#5F95FF",
                      "strokeWidth": 1,
                      "fill": "#fff",
                      "style": {
                        "visibility": "hidden"
                      }
                    }
                  }
                }
              },
              "items": [
                {
                  "group": "top",
                  "id": "cd33076b-c9ab-4c8c-93f1-59a6fa140057"
                },
                {
                  "group": "right",
                  "id": "b9f9b272-0668-4e27-aa14-24f4071fa355"
                },
                {
                  "group": "bottom",
                  "id": "1f4cc0aa-f9d8-43ee-8dfd-26622fef0b43"
                },
                {
                  "group": "left",
                  "id": "710c3232-471d-4fd6-8446-a1bd11ca6ab8"
                }
              ]
            },
            "id": "8cac2855-590e-4a82-bfba-26dae82f7f07",
            "zIndex": 1,
            "data": {
              "type": "tm.Actor",
              "name": "Doctor/Nurse",
              "description": "",
              "isTrustBoundary": false,
              "outOfScope": false,
              "reasonOutOfScope": "",
              "hasOpenThreats": false,
              "providesAuthentication": false,
              "threats": []
            }
          },
          {
            "position": {
              "x": 50,
              "y": 320
            },
            "size": {
              "width": 112.5,
              "height": 60
            },
            "attrs": {
              "text": {
                "text": "Admin Staff"
              },
              "body": {
                "stroke": "#333333",
                "strokeWidth": 1.5,
                "strokeDasharray": null
              }
            },
            "visible": true,
            "shape": "actor",
            "ports": {
              "groups": {
                "top": {
                  "position": "top",
                  "attrs": {
                    "circle": {
                      "r": 4,
                      "magnet": true,
                      "stroke": "#5F95FF",
                      "strokeWidth": 1,
                      "fill": "#fff",
                      "style": {
                        "visibility": "hidden"
                      }
                    }
                  }
                },
                "right": {
                  "position": "right",
                  "attrs": {
                    "circle": {
                      "r": 4,
                      "magnet": true,
                      "stroke": "#5F95FF",
                      "strokeWidth": 1,
                      "fill": "#fff",
                      "style": {
                        "visibility": "hidden"
                      }
                    }
                  }
                },
                "bottom": {
                  "position": "bottom",
                  "attrs": {
                    "circle": {
                      "r": 4,
                      "magnet": true,
                      "stroke": "#5F95FF",
                      "strokeWidth": 1,
                      "fill": "#fff",
                      "style": {
                        "visibility": "hidden"
                      }
                    }
                  }
                },
                "left": {
                  "position": "left",
                  "attrs": {
                    "circle": {
                      "r": 4,
                      "magnet": true,
                      "stroke": "#5F95FF",
                      "strokeWidth": 1,
                      "fill": "#fff",
                      "style": {
                        "visibility": "hidden"
                      }
                    }
                  }
                }
              },
              "items": [
                {
                  "group": "top",
                  "id": "cd33076b-c9ab-4c8c-93f1-59a6fa140057"
                },
                {
                  "group": "right",
                  "id": "b9f9b272-0668-4e27-aa14-24f4071fa355"
                },
                {
                  "group": "bottom",
                  "id": "1f4cc0aa-f9d8-43ee-8dfd-26622fef0b43"
                },
                {
                  "group": "left",
                  "id": "710c3232-471d-4fd6-8446-a1bd11ca6ab8"
                }
              ]
            },
            "id": "d1e8901f-8821-4285-8e95-d9af2bddfcf9",
            "zIndex": 2,
            "data": {
              "type": "tm.Actor",
              "name": "Admin Staff",
              "description": "",
              "isTrustBoundary": false,
              "outOfScope": false,
              "reasonOutOfScope": "",
              "hasOpenThreats": false,
              "providesAuthentication": false,
              "threats": []
            }
          },
          {
            "position": {
              "x": 50,
              "y": 150
            },
            "size": {
              "width": 112.5,
              "height": 60
            },
            "attrs": {
              "text": {
                "text": "Patient"
              },
              "body": {
                "stroke": "#333333",
                "strokeWidth": 1.5,
                "strokeDasharray": null
              }
            },
            "visible": true,
            "shape": "actor",
            "ports": {
              "groups": {
                "top": {
                  "position": "top",
                  "attrs": {
                    "circle": {
                      "r": 4,
                      "magnet": true,
                      "stroke": "#5F95FF",
                      "strokeWidth": 1,
                      "fill": "#fff",
                      "style": {
                        "visibility": "hidden"
                      }
                    }
                  }
                },
                "right": {
                  "position": "right",
                  "attrs": {
                    "circle": {
                      "r": 4,
                      "magnet": true,
                      "stroke": "#5F95FF",
                      "strokeWidth": 1,
                      "fill": "#fff",
                      "style": {
                        "visibility": "hidden"
                      }
                    }
                  }
                },
                "bottom": {
                  "position": "bottom",
                  "attrs": {
                    "circle": {
                      "r": 4,
                      "magnet": true,
                      "stroke": "#5F95FF",
                      "strokeWidth": 1,
                      "fill": "#fff",
                      "style": {
                        "visibility": "hidden"
                      }
                    }
                  }
                },
                "left": {
                  "position": "left",
                  "attrs": {
                    "circle": {
                      "r": 4,
                      "magnet": true,
                      "stroke": "#5F95FF",
                      "strokeWidth": 1,
                      "fill": "#fff",
                      "style": {
                        "visibility": "hidden"
                      }
                    }
                  }
                }
              },
              "items": [
                {
                  "group": "top",
                  "id": "cd33076b-c9ab-4c8c-93f1-59a6fa140057"
                },
                {
                  "group": "right",
                  "id": "b9f9b272-0668-4e27-aa14-24f4071fa355"
                },
                {
                  "group": "bottom",
                  "id": "1f4cc0aa-f9d8-43ee-8dfd-26622fef0b43"
                },
                {
                  "group": "left",
                  "id": "710c3232-471d-4fd6-8446-a1bd11ca6ab8"
                }
              ]
            },
            "id": "2b2debc6-2baf-45a4-8721-f9de611f954e",
            "zIndex": 3,
            "data": {
              "type": "tm.Actor",
              "name": "Patient",
              "description": "",
              "isTrustBoundary": false,
              "outOfScope": false,
              "reasonOutOfScope": "",
              "hasOpenThreats": false,
              "providesAuthentication": false,
              "threats": []
            }
          },
          {
            "position": {
              "x": 480,
              "y": 140
            },
            "size": {
              "width": 90,
              "height": 80
            },
            "attrs": {
              "text": {
                "text": "Patient\nPortal"
              },
              "body": {
                "stroke": "red",
                "strokeWidth": 2.5,
                "strokeDasharray": null
              }
            },
            "visible": true,
            "shape": "process",
            "ports": {
              "groups": {
                "top": {
                  "position": "top",
                  "attrs": {
                    "circle": {
                      "r": 4,
                      "magnet": true,
                      "stroke": "#5F95FF",
                      "strokeWidth": 1,
                      "fill": "#fff",
                      "style": {
                        "visibility": "hidden"
                      }
                    }
                  }
                },
                "right": {
                  "position": "right",
                  "attrs": {
                    "circle": {
                      "r": 4,
                      "magnet": true,
                      "stroke": "#5F95FF",
                      "strokeWidth": 1,
                      "fill": "#fff",
                      "style": {
                        "visibility": "hidden"
                      }
                    }
                  }
                },
                "bottom": {
                  "position": "bottom",
                  "attrs": {
                    "circle": {
                      "r": 4,
                      "magnet": true,
                      "stroke": "#5F95FF",
                      "strokeWidth": 1,
                      "fill": "#fff",
                      "style": {
                        "visibility": "hidden"
                      }
                    }
                  }
                },
                "left": {
                  "position": "left",
                  "attrs": {
                    "circle": {
                      "r": 4,
                      "magnet": true,
                      "stroke": "#5F95FF",
                      "strokeWidth": 1,
                      "fill": "#fff",
                      "style": {
                        "visibility": "hidden"
                      }
                    }
                  }
                }
              },
              "items": [
                {
                  "group": "top",
                  "id": "8b4398be-4a76-4963-abaf-846e1a5d8d7e"
                },
                {
                  "group": "right",
                  "id": "2b03da9d-d2e2-4f4a-9337-21cd2a2ab151"
                },
                {
                  "group": "bottom",
                  "id": "8340a496-e615-4719-b93e-6d27299885ae"
                },
                {
                  "group": "left",
                  "id": "46aa609d-dbae-4e8c-b38e-fc80508b758b"
                }
              ]
            },
            "id": "267b74c8-1333-46d1-a7ca-75720c33860f",
            "zIndex": 4,
            "data": {
              "type": "tm.Process",
              "name": "Patient\nPortal",
              "description": "",
              "outOfScope": false,
              "isTrustBoundary": false,
              "reasonOutOfScope": "",
              "hasOpenThreats": true,
              "handlesCardPayment": false,
              "handlesGoodsOrServices": false,
              "isWebApplication": false,
              "privilegeLevel": "",
              "threats": [
                {
                  "id": "5b26f270-05f9-4c62-8031-6a998fa811aa",
                  "title": "STRIDE threat 1",
                  "status": "Open",
                  "severity": "TBD",
                  "type": "Spoofing",
                  "description": "Fake login attempts via stolen credentials.",
                  "mitigation": "",
                  "modelType": "STRIDE",
                  "new": false,
                  "number": 1,
                  "score": ""
                },
                {
                  "id": "7d1363ab-0c19-45e1-8061-4724de2c8271",
                  "title": "STRIDE threat 2",
                  "status": "Open",
                  "severity": "TBD",
                  "type": "Tampering",
                  "description": "App traffic modified via MITM.",
                  "mitigation": "",
                  "modelType": "STRIDE",
                  "new": false,
                  "number": 2,
                  "score": ""
                },
                {
                  "id": "3c6b943d-804b-4511-854b-27c17d1e1f68",
                  "title": "STRIDE threat 3",
                  "status": "Open",
                  "severity": "TBD",
                  "type": "Information disclosure",
                  "description": "Leakage of medical records in transit.",
                  "mitigation": "",
                  "modelType": "STRIDE",
                  "new": false,
                  "number": 3,
                  "score": ""
                },
                {
                  "id": "3297ebd1-51c9-4e2b-92ee-72c75632fe10",
                  "title": "STRIDE threat 4",
                  "status": "Open",
                  "severity": "TBD",
                  "type": "Denial of service",
                  "description": "Attackers flood the app APIs.",
                  "mitigation": "",
                  "modelType": "STRIDE",
                  "new": false,
                  "number": 4,
                  "score": ""
                },
                {
                  "id": "6f9c592e-7306-4bb2-84fe-b38214b7ab3c",
                  "title": "STRIDE threat 5",
                  "status": "Open",
                  "severity": "TBD",
                  "type": "Elevation of privilege",
                  "description": "Non-patient accessing restricted data.",
                  "mitigation": "",
                  "modelType": "STRIDE",
                  "new": false,
                  "number": 5,
                  "score": ""
                }
              ],
              "threatFrequency": {
                "spoofing": 1,
                "tampering": 1,
                "repudiation": 0,
                "informationDisclosure": 1,
                "denialOfService": 1,
                "elevationOfPrivilege": 1
              }
            }
          },
          {
            "position": {
              "x": 262.5,
              "y": 310
            },
            "size": {
              "width": 80,
              "height": 80
            },
            "attrs": {
              "text": {
                "text": "Admin\nManagement\nSystem"
              },
              "body": {
                "stroke": "red",
                "strokeWidth": 2.5,
                "strokeDasharray": null
              }
            },
            "visible": true,
            "shape": "process",
            "ports": {
              "groups": {
                "top": {
                  "position": "top",
                  "attrs": {
                    "circle": {
                      "r": 4,
                      "magnet": true,
                      "stroke": "#5F95FF",
                      "strokeWidth": 1,
                      "fill": "#fff",
                      "style": {
                        "visibility": "hidden"
                      }
                    }
                  }
                },
                "right": {
                  "position": "right",
                  "attrs": {
                    "circle": {
                      "r": 4,
                      "magnet": true,
                      "stroke": "#5F95FF",
                      "strokeWidth": 1,
                      "fill": "#fff",
                      "style": {
                        "visibility": "hidden"
                      }
                    }
                  }
                },
                "bottom": {
                  "position": "bottom",
                  "attrs": {
                    "circle": {
                      "r": 4,
                      "magnet": true,
                      "stroke": "#5F95FF",
                      "strokeWidth": 1,
                      "fill": "#fff",
                      "style": {
                        "visibility": "hidden"
                      }
                    }
                  }
                },
                "left": {
                  "position": "left",
                  "attrs": {
                    "circle": {
                      "r": 4,
                      "magnet": true,
                      "stroke": "#5F95FF",
                      "strokeWidth": 1,
                      "fill": "#fff",
                      "style": {
                        "visibility": "hidden"
                      }
                    }
                  }
                }
              },
              "items": [
                {
                  "group": "top",
                  "id": "8b4398be-4a76-4963-abaf-846e1a5d8d7e"
                },
                {
                  "group": "right",
                  "id": "2b03da9d-d2e2-4f4a-9337-21cd2a2ab151"
                },
                {
                  "group": "bottom",
                  "id": "8340a496-e615-4719-b93e-6d27299885ae"
                },
                {
                  "group": "left",
                  "id": "46aa609d-dbae-4e8c-b38e-fc80508b758b"
                }
              ]
            },
            "id": "7fe6cd3a-dfc5-469b-b8e7-8e47991b8fde",
            "data": {
              "type": "tm.Process",
              "name": "Admin\nManagement\nSystem",
              "description": "",
              "outOfScope": false,
              "isTrustBoundary": false,
              "reasonOutOfScope": "",
              "hasOpenThreats": true,
              "handlesCardPayment": false,
              "handlesGoodsOrServices": false,
              "isWebApplication": false,
              "privilegeLevel": "",
              "threats": [
                {
                  "id": "72e52288-edf8-400c-bf42-a1fe177b8d16",
                  "title": "STRIDE threat 1",
                  "status": "Open",
                  "severity": "TBD",
                  "type": "Spoofing",
                  "description": "Attack on admin accounts.",
                  "mitigation": "",
                  "modelType": "STRIDE",
                  "new": false,
                  "number": 11,
                  "score": ""
                },
                {
                  "id": "f54b742f-d8aa-46a8-8932-a093578cfe16",
                  "title": "STRIDE threat 2",
                  "status": "Open",
                  "severity": "TBD",
                  "type": "Tampering",
                  "description": "Unauthorized role modifications.",
                  "mitigation": "",
                  "modelType": "STRIDE",
                  "new": false,
                  "number": 12,
                  "score": ""
                },
                {
                  "id": "d27a897b-b045-4255-b893-cf91d1ff72f2",
                  "title": "STRIDE threat 3",
                  "status": "Open",
                  "severity": "TBD",
                  "type": "Repudiation",
                  "description": "Admin denies modifications.",
                  "mitigation": "",
                  "modelType": "STRIDE",
                  "new": false,
                  "number": 13,
                  "score": ""
                },
                {
                  "id": "ed63fe95-075f-496d-8995-b57614b526b5",
                  "title": "STRIDE threat 4",
                  "status": "Open",
                  "severity": "TBD",
                  "type": "Elevation of privilege",
                  "description": "Regular user becomes admin.",
                  "mitigation": "",
                  "modelType": "STRIDE",
                  "new": false,
                  "number": 14,
                  "score": ""
                }
              ],
              "threatFrequency": {
                "spoofing": 1,
                "tampering": 1,
                "repudiation": 1,
                "informationDisclosure": 0,
                "denialOfService": 0,
                "elevationOfPrivilege": 1
              }
            },
            "zIndex": 6
          },
          {
            "position": {
              "x": 721,
              "y": 140
            },
            "size": {
              "width": 80,
              "height": 80
            },
            "attrs": {
              "text": {
                "text": "Authentication\nServer"
              },
              "body": {
                "stroke": "red",
                "strokeWidth": 2.5,
                "strokeDasharray": null
              }
            },
            "visible": true,
            "shape": "process",
            "ports": {
              "groups": {
                "top": {
                  "position": "top",
                  "attrs": {
                    "circle": {
                      "r": 4,
                      "magnet": true,
                      "stroke": "#5F95FF",
                      "strokeWidth": 1,
                      "fill": "#fff",
                      "style": {
                        "visibility": "hidden"
                      }
                    }
                  }
                },
                "right": {
                  "position": "right",
                  "attrs": {
                    "circle": {
                      "r": 4,
                      "magnet": true,
                      "stroke": "#5F95FF",
                      "strokeWidth": 1,
                      "fill": "#fff",
                      "style": {
                        "visibility": "hidden"
                      }
                    }
                  }
                },
                "bottom": {
                  "position": "bottom",
                  "attrs": {
                    "circle": {
                      "r": 4,
                      "magnet": true,
                      "stroke": "#5F95FF",
                      "strokeWidth": 1,
                      "fill": "#fff",
                      "style": {
                        "visibility": "hidden"
                      }
                    }
                  }
                },
                "left": {
                  "position": "left",
                  "attrs": {
                    "circle": {
                      "r": 4,
                      "magnet": true,
                      "stroke": "#5F95FF",
                      "strokeWidth": 1,
                      "fill": "#fff",
                      "style": {
                        "visibility": "hidden"
                      }
                    }
                  }
                }
              },
              "items": [
                {
                  "group": "top",
                  "id": "8b4398be-4a76-4963-abaf-846e1a5d8d7e"
                },
                {
                  "group": "right",
                  "id": "2b03da9d-d2e2-4f4a-9337-21cd2a2ab151"
                },
                {
                  "group": "bottom",
                  "id": "8340a496-e615-4719-b93e-6d27299885ae"
                },
                {
                  "group": "left",
                  "id": "46aa609d-dbae-4e8c-b38e-fc80508b758b"
                }
              ]
            },
            "id": "f30bd9cf-00ed-457d-a19a-170d4b62c651",
            "data": {
              "type": "tm.Process",
              "name": "Authentication\nServer",
              "description": "",
              "outOfScope": false,
              "isTrustBoundary": false,
              "reasonOutOfScope": "",
              "hasOpenThreats": true,
              "handlesCardPayment": false,
              "handlesGoodsOrServices": false,
              "isWebApplication": false,
              "privilegeLevel": "",
              "threats": [
                {
                  "id": "c3f8603d-e4b1-4199-99d7-3a66635e52eb",
                  "title": "STRIDE threat 1",
                  "status": "Open",
                  "severity": "TBD",
                  "type": "Spoofing",
                  "description": "Token forgery / credential stuffing.",
                  "mitigation": "",
                  "modelType": "STRIDE",
                  "new": false,
                  "number": 15,
                  "score": ""
                },
                {
                  "id": "882fcf81-806b-4fe8-b3a9-21a4ed826574",
                  "title": "STRIDE threat 2",
                  "status": "Open",
                  "severity": "TBD",
                  "type": "Tampering",
                  "description": "Token altered in transport.",
                  "mitigation": "",
                  "modelType": "STRIDE",
                  "new": false,
                  "number": 16,
                  "score": ""
                },
                {
                  "id": "7ee53438-313e-49d4-b6cc-62de939056e2",
                  "title": "STRIDE threat 3",
                  "status": "Open",
                  "severity": "TBD",
                  "type": "Denial of service",
                  "description": "Authentication service disruption.",
                  "mitigation": "",
                  "modelType": "STRIDE",
                  "new": false,
                  "number": 17,
                  "score": ""
                }
              ],
              "threatFrequency": {
                "spoofing": 1,
                "tampering": 1,
                "repudiation": 0,
                "informationDisclosure": 0,
                "denialOfService": 1,
                "elevationOfPrivilege": 0
              }
            },
            "zIndex": 7
          },
          {
            "position": {
              "x": 485,
              "y": 310
            },
            "size": {
              "width": 80,
              "height": 80
            },
            "attrs": {
              "text": {
                "text": "EHR\nBackend\nAPI"
              },
              "body": {
                "stroke": "red",
                "strokeWidth": 2.5,
                "strokeDasharray": null
              }
            },
            "visible": true,
            "shape": "process",
            "ports": {
              "groups": {
                "top": {
                  "position": "top",
                  "attrs": {
                    "circle": {
                      "r": 4,
                      "magnet": true,
                      "stroke": "#5F95FF",
                      "strokeWidth": 1,
                      "fill": "#fff",
                      "style": {
                        "visibility": "hidden"
                      }
                    }
                  }
                },
                "right": {
                  "position": "right",
                  "attrs": {
                    "circle": {
                      "r": 4,
                      "magnet": true,
                      "stroke": "#5F95FF",
                      "strokeWidth": 1,
                      "fill": "#fff",
                      "style": {
                        "visibility": "hidden"
                      }
                    }
                  }
                },
                "bottom": {
                  "position": "bottom",
                  "attrs": {
                    "circle": {
                      "r": 4,
                      "magnet": true,
                      "stroke": "#5F95FF",
                      "strokeWidth": 1,
                      "fill": "#fff",
                      "style": {
                        "visibility": "hidden"
                      }
                    }
                  }
                },
                "left": {
                  "position": "left",
                  "attrs": {
                    "circle": {
                      "r": 4,
                      "magnet": true,
                      "stroke": "#5F95FF",
                      "strokeWidth": 1,
                      "fill": "#fff",
                      "style": {
                        "visibility": "hidden"
                      }
                    }
                  }
                }
              },
              "items": [
                {
                  "group": "top",
                  "id": "8b4398be-4a76-4963-abaf-846e1a5d8d7e"
                },
                {
                  "group": "right",
                  "id": "2b03da9d-d2e2-4f4a-9337-21cd2a2ab151"
                },
                {
                  "group": "bottom",
                  "id": "8340a496-e615-4719-b93e-6d27299885ae"
                },
                {
                  "group": "left",
                  "id": "46aa609d-dbae-4e8c-b38e-fc80508b758b"
                }
              ]
            },
            "id": "fa00405b-01b1-414c-81e3-445bf9003239",
            "data": {
              "type": "tm.Process",
              "name": "EHR\nBackend\nAPI",
              "description": "",
              "outOfScope": false,
              "isTrustBoundary": false,
              "reasonOutOfScope": "",
              "hasOpenThreats": true,
              "handlesCardPayment": false,
              "handlesGoodsOrServices": false,
              "isWebApplication": false,
              "privilegeLevel": "",
              "threats": [
                {
                  "id": "99b57911-efb7-4347-bba8-0b22d7614760",
                  "title": "STRIDE threat 1",
                  "status": "Open",
                  "severity": "TBD",
                  "type": "Tampering",
                  "description": "API interception altering medical data.",
                  "mitigation": "",
                  "modelType": "STRIDE",
                  "new": false,
                  "number": 18,
                  "score": ""
                },
                {
                  "id": "1b5627ba-e580-431c-8ea3-ff81eb5c241e",
                  "title": "STRIDE threat 2",
                  "status": "Open",
                  "severity": "TBD",
                  "type": "Information disclosure",
                  "description": "Improper API authorization exposes records.",
                  "mitigation": "",
                  "modelType": "STRIDE",
                  "new": false,
                  "number": 19,
                  "score": ""
                },
                {
                  "id": "3fe8fd4e-961d-481c-b15b-df0bbf1aaef5",
                  "title": "STRIDE threat 3",
                  "status": "Open",
                  "severity": "TBD",
                  "type": "Denial of service",
                  "description": "Flooding API causing system downtime.",
                  "mitigation": "",
                  "modelType": "STRIDE",
                  "new": false,
                  "number": 20,
                  "score": ""
                },
                {
                  "id": "2d186e55-c155-4786-bc02-02c57bbf94dd",
                  "title": "STRIDE threat 4",
                  "status": "Open",
                  "severity": "TBD",
                  "type": "Elevation of privilege",
                  "description": "Unauthorized API use to modify EHR data.",
                  "mitigation": "",
                  "modelType": "STRIDE",
                  "new": false,
                  "number": 21,
                  "score": ""
                }
              ],
              "threatFrequency": {
                "spoofing": 0,
                "tampering": 1,
                "repudiation": 0,
                "informationDisclosure": 1,
                "denialOfService": 1,
                "elevationOfPrivilege": 1
              }
            },
            "zIndex": 8
          },
          {
            "position": {
              "x": 485,
              "y": 490
            },
            "size": {
              "width": 80,
              "height": 80
            },
            "attrs": {
              "text": {
                "text": "Hospital\nWeb\nApplication"
              },
              "body": {
                "stroke": "red",
                "strokeWidth": 2.5,
                "strokeDasharray": null
              }
            },
            "visible": true,
            "shape": "process",
            "ports": {
              "groups": {
                "top": {
                  "position": "top",
                  "attrs": {
                    "circle": {
                      "r": 4,
                      "magnet": true,
                      "stroke": "#5F95FF",
                      "strokeWidth": 1,
                      "fill": "#fff",
                      "style": {
                        "visibility": "hidden"
                      }
                    }
                  }
                },
                "right": {
                  "position": "right",
                  "attrs": {
                    "circle": {
                      "r": 4,
                      "magnet": true,
                      "stroke": "#5F95FF",
                      "strokeWidth": 1,
                      "fill": "#fff",
                      "style": {
                        "visibility": "hidden"
                      }
                    }
                  }
                },
                "bottom": {
                  "position": "bottom",
                  "attrs": {
                    "circle": {
                      "r": 4,
                      "magnet": true,
                      "stroke": "#5F95FF",
                      "strokeWidth": 1,
                      "fill": "#fff",
                      "style": {
                        "visibility": "hidden"
                      }
                    }
                  }
                },
                "left": {
                  "position": "left",
                  "attrs": {
                    "circle": {
                      "r": 4,
                      "magnet": true,
                      "stroke": "#5F95FF",
                      "strokeWidth": 1,
                      "fill": "#fff",
                      "style": {
                        "visibility": "hidden"
                      }
                    }
                  }
                }
              },
              "items": [
                {
                  "group": "top",
                  "id": "8b4398be-4a76-4963-abaf-846e1a5d8d7e"
                },
                {
                  "group": "right",
                  "id": "2b03da9d-d2e2-4f4a-9337-21cd2a2ab151"
                },
                {
                  "group": "bottom",
                  "id": "8340a496-e615-4719-b93e-6d27299885ae"
                },
                {
                  "group": "left",
                  "id": "46aa609d-dbae-4e8c-b38e-fc80508b758b"
                }
              ]
            },
            "id": "386bed30-a4dc-4ee3-9eb0-960b5be98929",
            "data": {
              "type": "tm.Process",
              "name": "Hospital\nWeb\nApplication",
              "description": "",
              "outOfScope": false,
              "isTrustBoundary": false,
              "reasonOutOfScope": "",
              "hasOpenThreats": true,
              "handlesCardPayment": false,
              "handlesGoodsOrServices": false,
              "isWebApplication": false,
              "privilegeLevel": "",
              "threats": [
                {
                  "id": "733d521c-2e57-486e-bfc3-9eede83fb5df",
                  "title": "STRIDE threat 1",
                  "status": "Open",
                  "severity": "TBD",
                  "type": "Spoofing",
                  "description": "Unauthorized access to doctor accounts.\n",
                  "mitigation": "",
                  "modelType": "STRIDE",
                  "new": false,
                  "number": 6,
                  "score": ""
                },
                {
                  "id": "da06d341-f57a-483d-ad19-3f044b9a86d5",
                  "title": "STRIDE threat 2",
                  "status": "Open",
                  "severity": "TBD",
                  "type": "Tampering",
                  "description": "Prescription/treatment data manipulated.",
                  "mitigation": "",
                  "modelType": "STRIDE",
                  "new": false,
                  "number": 7,
                  "score": ""
                },
                {
                  "id": "79d1b3b4-44df-4e0a-bcde-5a72451f247f",
                  "title": "STRIDE threat 3",
                  "status": "Open",
                  "severity": "TBD",
                  "type": "Repudiation",
                  "description": "Repudiation: Doctor denies having changed a record.",
                  "mitigation": "",
                  "modelType": "STRIDE",
                  "new": false,
                  "number": 8,
                  "score": ""
                },
                {
                  "id": "234e2391-07cf-4db7-a0e4-e859f0fbb2c1",
                  "title": "STRIDE threat 4",
                  "status": "Open",
                  "severity": "TBD",
                  "type": "Information disclosure",
                  "description": "Exposure of patient medical history.",
                  "mitigation": "",
                  "modelType": "STRIDE",
                  "new": false,
                  "number": 9,
                  "score": ""
                },
                {
                  "id": "69eb79c8-70f1-4e33-b7ad-968f8b474dd7",
                  "title": "STRIDE threat 5",
                  "status": "Open",
                  "severity": "TBD",
                  "type": "Elevation of privilege",
                  "description": "A nurse escalates permissions to doctor.",
                  "mitigation": "",
                  "modelType": "STRIDE",
                  "new": false,
                  "number": 10,
                  "score": ""
                }
              ],
              "threatFrequency": {
                "spoofing": 1,
                "tampering": 1,
                "repudiation": 1,
                "informationDisclosure": 1,
                "denialOfService": 0,
                "elevationOfPrivilege": 1
              }
            },
            "zIndex": 9
          },
          {
            "position": {
              "x": 721,
              "y": 270
            },
            "size": {
              "width": 120,
              "height": 60
            },
            "attrs": {
              "text": {
                "text": "EHR Database"
              },
              "topLine": {
                "stroke": "red",
                "strokeWidth": 2.5,
                "strokeDasharray": null
              },
              "bottomLine": {
                "stroke": "red",
                "strokeWidth": 2.5,
                "strokeDasharray": null
              }
            },
            "visible": true,
            "shape": "store",
            "ports": {
              "groups": {
                "top": {
                  "position": "top",
                  "attrs": {
                    "circle": {
                      "r": 4,
                      "magnet": true,
                      "stroke": "#5F95FF",
                      "strokeWidth": 1,
                      "fill": "#fff",
                      "style": {
                        "visibility": "hidden"
                      }
                    }
                  }
                },
                "right": {
                  "position": "right",
                  "attrs": {
                    "circle": {
                      "r": 4,
                      "magnet": true,
                      "stroke": "#5F95FF",
                      "strokeWidth": 1,
                      "fill": "#fff",
                      "style": {
                        "visibility": "hidden"
                      }
                    }
                  }
                },
                "bottom": {
                  "position": "bottom",
                  "attrs": {
                    "circle": {
                      "r": 4,
                      "magnet": true,
                      "stroke": "#5F95FF",
                      "strokeWidth": 1,
                      "fill": "#fff",
                      "style": {
                        "visibility": "hidden"
                      }
                    }
                  }
                },
                "left": {
                  "position": "left",
                  "attrs": {
                    "circle": {
                      "r": 4,
                      "magnet": true,
                      "stroke": "#5F95FF",
                      "strokeWidth": 1,
                      "fill": "#fff",
                      "style": {
                        "visibility": "hidden"
                      }
                    }
                  }
                }
              },
              "items": [
                {
                  "group": "top",
                  "id": "0fa136b5-ef08-49c1-9d94-a95e6cf27227"
                },
                {
                  "group": "right",
                  "id": "791373d4-7b86-42d9-b5fc-0fd79016eaeb"
                },
                {
                  "group": "bottom",
                  "id": "dc3a81ac-3e14-4124-b669-af84dc193c3d"
                },
                {
                  "group": "left",
                  "id": "e8ce3a3b-5e77-413c-a89d-a139423392c1"
                }
              ]
            },
            "id": "5fa8834f-647c-4cbc-85cc-0d424fa5d147",
            "zIndex": 10,
            "data": {
              "type": "tm.Store",
              "name": "EHR Database",
              "description": "",
              "outOfScope": false,
              "isTrustBoundary": false,
              "reasonOutOfScope": "",
              "hasOpenThreats": true,
              "isALog": false,
              "isEncrypted": false,
              "isSigned": false,
              "storesCredentials": false,
              "storesInventory": false,
              "threats": [
                {
                  "id": "ee8acc35-b67f-47e9-81e8-b72ac03f73dd",
                  "title": "STRIDE threat 1",
                  "status": "Open",
                  "severity": "TBD",
                  "type": "Tampering",
                  "description": "Medical records altered or deleted.",
                  "mitigation": "",
                  "modelType": "STRIDE",
                  "new": false,
                  "number": 22,
                  "score": ""
                },
                {
                  "id": "f3543e85-2229-476e-af9a-b0da03b5bfa0",
                  "title": "STRIDE threat 2",
                  "status": "Open",
                  "severity": "TBD",
                  "type": "Information disclosure",
                  "description": "Database leak exposing all patient info.",
                  "mitigation": "",
                  "modelType": "STRIDE",
                  "new": false,
                  "number": 23,
                  "score": ""
                },
                {
                  "id": "fcfe4738-738e-439b-83b8-66bc713d088b",
                  "title": "STRIDE threat 3",
                  "status": "Open",
                  "severity": "TBD",
                  "type": "Denial of service",
                  "description": "Database lock or overload.",
                  "mitigation": "",
                  "modelType": "STRIDE",
                  "new": false,
                  "number": 24,
                  "score": ""
                }
              ],
              "threatFrequency": {
                "tampering": 1,
                "repudiation": 0,
                "informationDisclosure": 1,
                "denialOfService": 1
              }
            }
          },
          {
            "shape": "flow",
            "attrs": {
              "line": {
                "stroke": "#333333",
                "targetMarker": {
                  "name": "block"
                },
                "sourceMarker": {
                  "name": ""
                },
                "strokeDasharray": null
              }
            },
            "width": 200,
            "height": 100,
            "zIndex": 10,
            "connector": "smooth",
            "data": {
              "type": "tm.Flow",
              "name": "Login\nRequest",
              "description": "",
              "outOfScope": false,
              "isTrustBoundary": false,
              "reasonOutOfScope": "",
              "hasOpenThreats": false,
              "isBidirectional": false,
              "isEncrypted": false,
              "isPublicNetwork": false,
              "protocol": "",
              "threats": []
            },
            "labels": [
              "Login\nRequest"
            ],
            "id": "cd96b384-8e0d-4d82-92af-80f6981abc78",
            "source": {
              "cell": "2b2debc6-2baf-45a4-8721-f9de611f954e",
              "port": "b9f9b272-0668-4e27-aa14-24f4071fa355"
            },
            "target": {
              "cell": "267b74c8-1333-46d1-a7ca-75720c33860f",
              "port": "46aa609d-dbae-4e8c-b38e-fc80508b758b"
            },
            "vertices": [
              {
                "x": 320,
                "y": 120
              }
            ]
          },
          {
            "shape": "flow",
            "attrs": {
              "line": {
                "stroke": "#333333",
                "targetMarker": {
                  "name": "block"
                },
                "sourceMarker": {
                  "name": ""
                },
                "strokeDasharray": null
              }
            },
            "width": 200,
            "height": 100,
            "zIndex": 10,
            "connector": "smooth",
            "data": {
              "type": "tm.Flow",
              "name": "Authentication\nRequest",
              "description": "",
              "outOfScope": false,
              "isTrustBoundary": false,
              "reasonOutOfScope": "",
              "hasOpenThreats": false,
              "isBidirectional": false,
              "isEncrypted": false,
              "isPublicNetwork": false,
              "protocol": "",
              "threats": []
            },
            "labels": [
              "Authentication\nRequest"
            ],
            "id": "fff08b75-4a33-499e-a90f-d1244a9f3582",
            "source": {
              "cell": "267b74c8-1333-46d1-a7ca-75720c33860f",
              "port": "2b03da9d-d2e2-4f4a-9337-21cd2a2ab151"
            },
            "target": {
              "cell": "f30bd9cf-00ed-457d-a19a-170d4b62c651",
              "port": "46aa609d-dbae-4e8c-b38e-fc80508b758b"
            },
            "vertices": []
          },
          {
            "shape": "flow",
            "attrs": {
              "line": {
                "stroke": "#333333",
                "targetMarker": {
                  "name": "block"
                },
                "sourceMarker": {
                  "name": ""
                },
                "strokeDasharray": null
              }
            },
            "width": 200,
            "height": 100,
            "zIndex": 10,
            "connector": "smooth",
            "data": {
              "type": "tm.Flow",
              "name": "Authentication\nToken",
              "description": "",
              "outOfScope": false,
              "isTrustBoundary": false,
              "reasonOutOfScope": "",
              "hasOpenThreats": false,
              "isBidirectional": false,
              "isEncrypted": false,
              "isPublicNetwork": false,
              "protocol": "",
              "threats": []
            },
            "labels": [
              "Authentication\nToken"
            ],
            "id": "15d18b26-3f34-4e9d-9166-fc587a7c9fb3",
            "source": {
              "cell": "f30bd9cf-00ed-457d-a19a-170d4b62c651",
              "port": "8b4398be-4a76-4963-abaf-846e1a5d8d7e"
            },
            "target": {
              "cell": "267b74c8-1333-46d1-a7ca-75720c33860f",
              "port": "8b4398be-4a76-4963-abaf-846e1a5d8d7e"
            },
            "vertices": [
              {
                "x": 640,
                "y": 110
              }
            ]
          },
          {
            "shape": "flow",
            "attrs": {
              "line": {
                "stroke": "#333333",
                "targetMarker": {
                  "name": "block"
                },
                "sourceMarker": {
                  "name": ""
                },
                "strokeDasharray": null
              }
            },
            "width": 200,
            "height": 100,
            "zIndex": 10,
            "connector": "smooth",
            "data": {
              "type": "tm.Flow",
              "name": "View Appointment\nMedical Records",
              "description": "",
              "outOfScope": false,
              "isTrustBoundary": false,
              "reasonOutOfScope": "",
              "hasOpenThreats": false,
              "isBidirectional": false,
              "isEncrypted": false,
              "isPublicNetwork": false,
              "protocol": "",
              "threats": []
            },
            "labels": [
              "View Appointment\nMedical Records"
            ],
            "id": "73e17640-dd0e-4c66-93bf-74293bf11d37",
            "source": {
              "cell": "2b2debc6-2baf-45a4-8721-f9de611f954e",
              "port": "b9f9b272-0668-4e27-aa14-24f4071fa355"
            },
            "target": {
              "cell": "267b74c8-1333-46d1-a7ca-75720c33860f",
              "port": "46aa609d-dbae-4e8c-b38e-fc80508b758b"
            },
            "vertices": [
              {
                "x": 330,
                "y": 230
              }
            ]
          },
          {
            "shape": "flow",
            "attrs": {
              "line": {
                "stroke": "#333333",
                "targetMarker": {
                  "name": "block"
                },
                "sourceMarker": {
                  "name": ""
                },
                "strokeDasharray": null
              }
            },
            "width": 200,
            "height": 100,
            "zIndex": 10,
            "connector": "smooth",
            "data": {
              "type": "tm.Flow",
              "name": "Get Patient Data",
              "description": "",
              "outOfScope": false,
              "isTrustBoundary": false,
              "reasonOutOfScope": "",
              "hasOpenThreats": false,
              "isBidirectional": false,
              "isEncrypted": false,
              "isPublicNetwork": false,
              "protocol": "",
              "threats": []
            },
            "labels": [
              "Get Patient Data"
            ],
            "id": "2546aedb-659a-4340-a376-31a53a588856",
            "source": {
              "cell": "267b74c8-1333-46d1-a7ca-75720c33860f",
              "port": "8340a496-e615-4719-b93e-6d27299885ae"
            },
            "target": {
              "cell": "fa00405b-01b1-414c-81e3-445bf9003239",
              "port": "8b4398be-4a76-4963-abaf-846e1a5d8d7e"
            },
            "vertices": []
          },
          {
            "shape": "flow",
            "attrs": {
              "line": {
                "stroke": "#333333",
                "targetMarker": {
                  "name": "block"
                },
                "sourceMarker": {
                  "name": ""
                },
                "strokeDasharray": null
              }
            },
            "width": 200,
            "height": 100,
            "zIndex": 10,
            "connector": "smooth",
            "data": {
              "type": "tm.Flow",
              "name": "Medical Record Update",
              "description": "",
              "outOfScope": false,
              "isTrustBoundary": false,
              "reasonOutOfScope": "",
              "hasOpenThreats": false,
              "isBidirectional": false,
              "isEncrypted": false,
              "isPublicNetwork": false,
              "protocol": "",
              "threats": []
            },
            "labels": [
              "Medical Record Update"
            ],
            "id": "16cf2656-cfbe-42f6-8ad4-63a50b90ad0e",
            "source": {
              "cell": "386bed30-a4dc-4ee3-9eb0-960b5be98929",
              "port": "8b4398be-4a76-4963-abaf-846e1a5d8d7e"
            },
            "target": {
              "cell": "fa00405b-01b1-414c-81e3-445bf9003239",
              "port": "8340a496-e615-4719-b93e-6d27299885ae"
            },
            "vertices": []
          },
          {
            "shape": "flow",
            "attrs": {
              "line": {
                "stroke": "#333333",
                "targetMarker": {
                  "name": "block"
                },
                "sourceMarker": {
                  "name": ""
                },
                "strokeDasharray": null
              }
            },
            "width": 200,
            "height": 100,
            "zIndex": 10,
            "connector": "smooth",
            "data": {
              "type": "tm.Flow",
              "name": "Update Treatment\nPrescriptions",
              "description": "",
              "outOfScope": false,
              "isTrustBoundary": false,
              "reasonOutOfScope": "",
              "hasOpenThreats": false,
              "isBidirectional": false,
              "isEncrypted": false,
              "isPublicNetwork": false,
              "protocol": "",
              "threats": []
            },
            "labels": [
              "Update Treatment\nPrescriptions"
            ],
            "id": "aa42665c-74f6-49e1-8007-2a2535eb2019",
            "source": {
              "cell": "8cac2855-590e-4a82-bfba-26dae82f7f07",
              "port": "b9f9b272-0668-4e27-aa14-24f4071fa355"
            },
            "target": {
              "cell": "386bed30-a4dc-4ee3-9eb0-960b5be98929",
              "port": "46aa609d-dbae-4e8c-b38e-fc80508b758b"
            },
            "vertices": []
          },
          {
            "shape": "flow",
            "attrs": {
              "line": {
                "stroke": "#333333",
                "targetMarker": {
                  "name": "block"
                },
                "sourceMarker": {
                  "name": ""
                },
                "strokeDasharray": null
              }
            },
            "width": 200,
            "height": 100,
            "zIndex": 10,
            "connector": "smooth",
            "data": {
              "type": "tm.Flow",
              "name": "Role\nManagement\nRequest",
              "description": "",
              "outOfScope": false,
              "isTrustBoundary": false,
              "reasonOutOfScope": "",
              "hasOpenThreats": false,
              "isBidirectional": false,
              "isEncrypted": false,
              "isPublicNetwork": false,
              "protocol": "",
              "threats": []
            },
            "labels": [
              "Role\nManagement\nRequest"
            ],
            "id": "aaeaa6a3-cfeb-4d1c-95aa-858e1fcd2445",
            "source": {
              "cell": "7fe6cd3a-dfc5-469b-b8e7-8e47991b8fde",
              "port": "2b03da9d-d2e2-4f4a-9337-21cd2a2ab151"
            },
            "target": {
              "cell": "fa00405b-01b1-414c-81e3-445bf9003239",
              "port": "46aa609d-dbae-4e8c-b38e-fc80508b758b"
            },
            "vertices": []
          },
          {
            "shape": "flow",
            "attrs": {
              "line": {
                "stroke": "#333333",
                "targetMarker": {
                  "name": "block"
                },
                "sourceMarker": {
                  "name": ""
                },
                "strokeDasharray": null
              }
            },
            "width": 200,
            "height": 100,
            "zIndex": 10,
            "connector": "smooth",
            "data": {
              "type": "tm.Flow",
              "name": "Login",
              "description": "",
              "outOfScope": false,
              "isTrustBoundary": false,
              "reasonOutOfScope": "",
              "hasOpenThreats": false,
              "isBidirectional": false,
              "isEncrypted": false,
              "isPublicNetwork": false,
              "protocol": "",
              "threats": []
            },
            "labels": [
              "Login"
            ],
            "id": "85ccc5df-a28f-4ac0-bffe-7a189e9ecef2",
            "source": {
              "cell": "d1e8901f-8821-4285-8e95-d9af2bddfcf9",
              "port": "b9f9b272-0668-4e27-aa14-24f4071fa355"
            },
            "target": {
              "cell": "7fe6cd3a-dfc5-469b-b8e7-8e47991b8fde",
              "port": "46aa609d-dbae-4e8c-b38e-fc80508b758b"
            },
            "vertices": []
          },
          {
            "shape": "flow",
            "attrs": {
              "line": {
                "stroke": "#333333",
                "targetMarker": {
                  "name": "block"
                },
                "sourceMarker": {
                  "name": ""
                },
                "strokeDasharray": null
              }
            },
            "width": 200,
            "height": 100,
            "zIndex": 10,
            "connector": "smooth",
            "data": {
              "type": "tm.Flow",
              "name": "Validate\nCredentials",
              "description": "",
              "outOfScope": false,
              "isTrustBoundary": false,
              "reasonOutOfScope": "",
              "hasOpenThreats": false,
              "isBidirectional": false,
              "isEncrypted": false,
              "isPublicNetwork": false,
              "protocol": "",
              "threats": []
            },
            "labels": [
              "Validate\nCredentials"
            ],
            "id": "0cfb31ac-e66c-4946-8e3f-66bc41ac5208",
            "source": {
              "cell": "f30bd9cf-00ed-457d-a19a-170d4b62c651",
              "port": "2b03da9d-d2e2-4f4a-9337-21cd2a2ab151"
            },
            "target": {
              "cell": "9593c0de-8d00-4e40-a59a-b4b867ffd549",
              "port": "e8ce3a3b-5e77-413c-a89d-a139423392c1"
            },
            "vertices": []
          },
          {
            "shape": "flow",
            "attrs": {
              "line": {
                "stroke": "#333333",
                "targetMarker": {
                  "name": "block"
                },
                "sourceMarker": {
                  "name": ""
                },
                "strokeDasharray": null
              }
            },
            "width": 200,
            "height": 100,
            "zIndex": 10,
            "connector": "smooth",
            "data": {
              "type": "tm.Flow",
              "name": "Read/Write EHR Data",
              "description": "",
              "outOfScope": false,
              "isTrustBoundary": false,
              "reasonOutOfScope": "",
              "hasOpenThreats": false,
              "isBidirectional": false,
              "isEncrypted": false,
              "isPublicNetwork": false,
              "protocol": "",
              "threats": []
            },
            "labels": [
              "Read/Write EHR Data"
            ],
            "id": "2d9aa9c2-ca85-4cb2-abee-cb46b74401c2",
            "source": {
              "cell": "fa00405b-01b1-414c-81e3-445bf9003239",
              "port": "2b03da9d-d2e2-4f4a-9337-21cd2a2ab151"
            },
            "target": {
              "cell": "5fa8834f-647c-4cbc-85cc-0d424fa5d147",
              "port": "e8ce3a3b-5e77-413c-a89d-a139423392c1"
            },
            "vertices": []
          },
          {
            "shape": "flow",
            "attrs": {
              "line": {
                "stroke": "#333333",
                "targetMarker": {
                  "name": "block"
                },
                "sourceMarker": {
                  "name": ""
                },
                "strokeDasharray": null
              }
            },
            "width": 200,
            "height": 100,
            "zIndex": 10,
            "connector": "smooth",
            "data": {
              "type": "tm.Flow",
              "name": "Write Audit Logs",
              "description": "",
              "outOfScope": false,
              "isTrustBoundary": false,
              "reasonOutOfScope": "",
              "hasOpenThreats": false,
              "isBidirectional": false,
              "isEncrypted": false,
              "isPublicNetwork": false,
              "protocol": "",
              "threats": []
            },
            "labels": [
              "Write Audit Logs"
            ],
            "id": "52a539b0-e2da-4b68-be5d-5b4322e5f731",
            "source": {
              "cell": "fa00405b-01b1-414c-81e3-445bf9003239",
              "port": "2b03da9d-d2e2-4f4a-9337-21cd2a2ab151"
            },
            "target": {
              "cell": "14a6beb2-1baa-4366-a051-3cca96392e14",
              "port": "e8ce3a3b-5e77-413c-a89d-a139423392c1"
            },
            "vertices": []
          },
          {
            "position": {
              "x": 931,
              "y": 150
            },
            "size": {
              "width": 120,
              "height": 60
            },
            "attrs": {
              "text": {
                "text": "User Accounts\nDatabase"
              },
              "topLine": {
                "stroke": "red",
                "strokeWidth": 2.5,
                "strokeDasharray": null
              },
              "bottomLine": {
                "stroke": "red",
                "strokeWidth": 2.5,
                "strokeDasharray": null
              }
            },
            "visible": true,
            "shape": "store",
            "ports": {
              "groups": {
                "top": {
                  "position": "top",
                  "attrs": {
                    "circle": {
                      "r": 4,
                      "magnet": true,
                      "stroke": "#5F95FF",
                      "strokeWidth": 1,
                      "fill": "#fff",
                      "style": {
                        "visibility": "hidden"
                      }
                    }
                  }
                },
                "right": {
                  "position": "right",
                  "attrs": {
                    "circle": {
                      "r": 4,
                      "magnet": true,
                      "stroke": "#5F95FF",
                      "strokeWidth": 1,
                      "fill": "#fff",
                      "style": {
                        "visibility": "hidden"
                      }
                    }
                  }
                },
                "bottom": {
                  "position": "bottom",
                  "attrs": {
                    "circle": {
                      "r": 4,
                      "magnet": true,
                      "stroke": "#5F95FF",
                      "strokeWidth": 1,
                      "fill": "#fff",
                      "style": {
                        "visibility": "hidden"
                      }
                    }
                  }
                },
                "left": {
                  "position": "left",
                  "attrs": {
                    "circle": {
                      "r": 4,
                      "magnet": true,
                      "stroke": "#5F95FF",
                      "strokeWidth": 1,
                      "fill": "#fff",
                      "style": {
                        "visibility": "hidden"
                      }
                    }
                  }
                }
              },
              "items": [
                {
                  "group": "top",
                  "id": "0fa136b5-ef08-49c1-9d94-a95e6cf27227"
                },
                {
                  "group": "right",
                  "id": "791373d4-7b86-42d9-b5fc-0fd79016eaeb"
                },
                {
                  "group": "bottom",
                  "id": "dc3a81ac-3e14-4124-b669-af84dc193c3d"
                },
                {
                  "group": "left",
                  "id": "e8ce3a3b-5e77-413c-a89d-a139423392c1"
                }
              ]
            },
            "id": "9593c0de-8d00-4e40-a59a-b4b867ffd549",
            "data": {
              "type": "tm.Store",
              "name": "User Accounts\nDatabase",
              "description": "",
              "outOfScope": false,
              "isTrustBoundary": false,
              "reasonOutOfScope": "",
              "hasOpenThreats": true,
              "isALog": false,
              "isEncrypted": false,
              "isSigned": false,
              "storesCredentials": false,
              "storesInventory": false,
              "threats": [
                {
                  "id": "10e42070-2fce-4846-8ab9-3a8b3f7dac0b",
                  "title": "STRIDE threat 1",
                  "status": "Open",
                  "severity": "TBD",
                  "type": "Tampering",
                  "description": "Password hashes modified.",
                  "mitigation": "",
                  "modelType": "STRIDE",
                  "new": false,
                  "number": 27,
                  "score": ""
                },
                {
                  "id": "673d3937-9470-4ccf-bb68-0830348c6f90",
                  "title": "STRIDE threat 2",
                  "status": "Open",
                  "severity": "TBD",
                  "type": "Information disclosure",
                  "description": "Leaking passwords or authentication details.",
                  "mitigation": "",
                  "modelType": "STRIDE",
                  "new": false,
                  "number": 28,
                  "score": ""
                }
              ],
              "threatFrequency": {
                "tampering": 1,
                "repudiation": 0,
                "informationDisclosure": 1,
                "denialOfService": 0
              }
            },
            "zIndex": 11,
            "tools": {
              "items": [
                "boundary",
                "button-remove"
              ],
              "name": null
            }
          },
          {
            "position": {
              "x": 721,
              "y": 410
            },
            "size": {
              "width": 120,
              "height": 60
            },
            "attrs": {
              "text": {
                "text": "Audit Log\nStorage"
              },
              "topLine": {
                "stroke": "red",
                "strokeWidth": 2.5,
                "strokeDasharray": null
              },
              "bottomLine": {
                "stroke": "red",
                "strokeWidth": 2.5,
                "strokeDasharray": null
              }
            },
            "visible": true,
            "shape": "store",
            "ports": {
              "groups": {
                "top": {
                  "position": "top",
                  "attrs": {
                    "circle": {
                      "r": 4,
                      "magnet": true,
                      "stroke": "#5F95FF",
                      "strokeWidth": 1,
                      "fill": "#fff",
                      "style": {
                        "visibility": "hidden"
                      }
                    }
                  }
                },
                "right": {
                  "position": "right",
                  "attrs": {
                    "circle": {
                      "r": 4,
                      "magnet": true,
                      "stroke": "#5F95FF",
                      "strokeWidth": 1,
                      "fill": "#fff",
                      "style": {
                        "visibility": "hidden"
                      }
                    }
                  }
                },
                "bottom": {
                  "position": "bottom",
                  "attrs": {
                    "circle": {
                      "r": 4,
                      "magnet": true,
                      "stroke": "#5F95FF",
                      "strokeWidth": 1,
                      "fill": "#fff",
                      "style": {
                        "visibility": "hidden"
                      }
                    }
                  }
                },
                "left": {
                  "position": "left",
                  "attrs": {
                    "circle": {
                      "r": 4,
                      "magnet": true,
                      "stroke": "#5F95FF",
                      "strokeWidth": 1,
                      "fill": "#fff",
                      "style": {
                        "visibility": "hidden"
                      }
                    }
                  }
                }
              },
              "items": [
                {
                  "group": "top",
                  "id": "0fa136b5-ef08-49c1-9d94-a95e6cf27227"
                },
                {
                  "group": "right",
                  "id": "791373d4-7b86-42d9-b5fc-0fd79016eaeb"
                },
                {
                  "group": "bottom",
                  "id": "dc3a81ac-3e14-4124-b669-af84dc193c3d"
                },
                {
                  "group": "left",
                  "id": "e8ce3a3b-5e77-413c-a89d-a139423392c1"
                }
              ]
            },
            "id": "14a6beb2-1baa-4366-a051-3cca96392e14",
            "zIndex": 12,
            "data": {
              "type": "tm.Store",
              "name": "Audit Log\nStorage",
              "description": "",
              "outOfScope": false,
              "isTrustBoundary": false,
              "reasonOutOfScope": "",
              "hasOpenThreats": true,
              "isALog": false,
              "isEncrypted": false,
              "isSigned": false,
              "storesCredentials": false,
              "storesInventory": false,
              "threats": [
                {
                  "id": "89ee4227-33ad-4782-91e2-a99ab9359915",
                  "title": "STRIDE threat 1",
                  "status": "Open",
                  "severity": "TBD",
                  "type": "Repudiation",
                  "description": "Logs deleted or altered.",
                  "mitigation": "",
                  "modelType": "STRIDE",
                  "new": false,
                  "number": 25,
                  "score": ""
                },
                {
                  "id": "0b9bb685-6a16-46f8-9820-dbac1cbec893",
                  "title": "STRIDE threat 2",
                  "status": "Open",
                  "severity": "TBD",
                  "type": "Tampering",
                  "description": "Attackers modify logs to hide tracks.",
                  "mitigation": "",
                  "modelType": "STRIDE",
                  "new": false,
                  "number": 26,
                  "score": ""
                }
              ],
              "threatFrequency": {
                "tampering": 1,
                "repudiation": 1,
                "informationDisclosure": 0,
                "denialOfService": 0
              }
            }
          }
        ]
      }
    ],
    "diagramTop": 1,
    "reviewer": "",
    "threatTop": 28
  }
}